management/__init__.py
management/commands/__init__.py
management/commands/rabbit_consumer.py
migrations/0001_initial.py
migrations/__init__.py
sso_server/__init__.py
sso_server/admin.py
sso_server/apps.py
sso_server/get_student_info.py
sso_server/middleware.py
sso_server/models.py
sso_server/token_service.py
sso_server/urls.py
sso_server/utils.py
sso_server/views.py
sso_server/management/__init__.py
sso_server/management/commands/__init__.py
sso_server/management/commands/rabbit_consumer.py
sso_server/migrations/0001_initial.py
sso_server/migrations/__init__.py
sso_server/services/__init__.py
sso_server/services/get_student_info.py
sso_server/services/token_service.py
kodland_sso_server-0.3.0.dist-info/LICENSE
kodland_sso_server-0.3.0.dist-info/METADATA
kodland_sso_server-0.3.0.dist-info/WHEEL
kodland_sso_server-0.3.0.dist-info/top_level.txt
kodland_sso_server-0.3.0.dist-info/RECORD
