Metadata-Version: 2.1
Name: kodland-sso-server
Version: 0.3.0
Summary: Django sso server package for Kodland
Home-page: UNKNOWN
Author: Dmitry Shoytov
Author-email: shoytov@gmail.com
License: UNKNOWN
Platform: UNKNOWN
Classifier: Programming Language :: Python :: 3
Classifier: License :: OSI Approved :: MIT License
Classifier: Operating System :: OS Independent
Requires-Python: >=3.6
Requires-Dist: django (==2.0.1)
Requires-Dist: djangorestframework (==3.11.2)
Requires-Dist: django-rest-swagger (==2.2.0)
Requires-Dist: pika (==1.2.0)
